{
  "page": 113,
  "value": [
    {
      "path": "_news/2013-07-04-from-chess-to-ping-pong-how-pegasystems-is-capturing-the-fortune-500.md",
      "title": "From chess to ping pong: How Pegasystems is capturing the Fortune 500",
      "excerpt": "And Cisco is using the technology to centralise its business processes in a company-wide rules engine that will help it respond ... and refine and develop them until they meet the needs of the ...",
      "heat": 142,
      "tags": null,
      "type": "article",
      "webUrl": "https://www.computerweekly.com/feature/How-Pegasystems-is-capturing-the-Fortune-500",
      "ampWebUrl": "https://www.computerweekly.com/feature/How-Pegasystems-is-capturing-the-Fortune-500?amp=1",
      "cdnAmpWebUrl": "https://www-computerweekly-com.cdn.ampproject.org/c/s/www.computerweekly.com/feature/How-Pegasystems-is-capturing-the-Fortune-500?amp=1",
      "publishedDateTime": "2013-07-04T09:36:00-07:00",
      "updatedDateTime": null,
      "provider": {
        "name": "Computer Weekly",
        "domain": "computerweekly.com",
        "images": null,
        "publishers": null,
        "authors": null
      },
      "images": [
        {
          "url": "https://cdn.ttgtmedia.com/rms/editorial/Alan-Pegasystems.jpg",
          "width": 580,
          "height": 387,
          "title": "From chess to ping pong: How Pegasystems is capturing the Fortune 500",
          "attribution": null
        }
      ],
      "locale": "en-us",
      "categories": [
        "news"
      ],
      "topics": [
        "AI"
      ]
    }
  ],
  "nextPage": null
}