{
  "page": 1,
  "value": [
    {
      "path": "_news/2020-04-01-human-layer-cybersecurity-and-ai-thwart-data-breaches-vb-live.md",
      "title": "“Human-layer” cybersecurity and AI thwart data breaches (VB Live)",
      "excerpt": "Data breaches are at an all-time high, because traditional cybersecurity methods just can’t predict human behavior. Learn how stateful machine learning delivers a robust, people-centric approach to cybersecurity when you access this free VB Live event! Access on demand here! Over the past decade companies have been boosting their ...",
      "heat": 87,
      "tags": null,
      "type": "article",
      "webUrl": "https://venturebeat.com/2020/04/01/human-layer-cybersecurity-and-ai-thwart-data-breaches-vb-live/",
      "ampWebUrl": "https://venturebeat.com/2020/04/01/human-layer-cybersecurity-and-ai-thwart-data-breaches-vb-live/amp/",
      "cdnAmpWebUrl": "https://venturebeat-com.cdn.ampproject.org/c/s/venturebeat.com/2020/04/01/human-layer-cybersecurity-and-ai-thwart-data-breaches-vb-live/amp/",
      "publishedDateTime": "2020-04-01T16:54:00-07:00",
      "updatedDateTime": null,
      "provider": {
        "name": "VentureBeat",
        "domain": "venturebeat.com",
        "images": [
          {
            "url": "https://insideout.app/ai/assets/images/organizations/venturebeat.com-50x50.jpg",
            "width": 50,
            "height": 50,
            "title": null,
            "attribution": null
          }
        ],
        "publishers": null,
        "authors": null
      },
      "images": [
        {
          "url": "https://venturebeat.com/wp-content/uploads/2020/04/GettyImages-1022805724.jpg?fit=840%2C415&strip=all",
          "width": 840,
          "height": 415,
          "title": "“Human-layer” cybersecurity and AI thwart data breaches (VB Live)",
          "attribution": null
        }
      ],
      "locale": "en-us",
      "categories": [
        "news"
      ],
      "topics": [
        "AI"
      ]
    },
    {
      "path": "_news/2020-04-01-it-took-a-coronavirus-outbreak-for-self-driving-cars-to-become-more-appealing.md",
      "title": "It took a coronavirus outbreak for self-driving cars to become more appealing",
      "excerpt": "Suddenly, a future full of self-driving cars isn't just a sci-fi pipe dream. What used to be considered a scary, uncertain technology for many Americans looks more like an effective tool to protect ourselves from a fast-spreading, infectious disease. With COVID-19 — the name for the disease caused by the new coronavirus — keeping most of ...",
      "heat": 71,
      "tags": null,
      "type": "article",
      "webUrl": "https://mashable.com/article/autonomous-vehicle-perception-coronavirus/",
      "ampWebUrl": "https://mashable.com/article/autonomous-vehicle-perception-coronavirus.amp",
      "cdnAmpWebUrl": "https://mashable-com.cdn.ampproject.org/c/s/mashable.com/article/autonomous-vehicle-perception-coronavirus.amp",
      "publishedDateTime": "2020-04-01T16:07:00-07:00",
      "updatedDateTime": null,
      "provider": {
        "name": "Mashable",
        "domain": "mashable.com",
        "images": null,
        "publishers": null,
        "authors": null
      },
      "images": [
        {
          "url": "https://mondrian.mashable.com/2020%252F04%252F01%252F6c%252F16342e756b0e4023b82a7862df64d273.068ba.png%252F1200x630.png?signature=0rYR5J06AcdSItqbZjuNXcbd5EQ=",
          "width": 1200,
          "height": 630,
          "title": "It took a coronavirus outbreak for self-driving cars to become more appealing",
          "attribution": null
        }
      ],
      "locale": "en-us",
      "categories": [
        "news"
      ],
      "topics": [
        "AI in Autos",
        "AI"
      ]
    },
    {
      "path": "_news/2020-04-01-30-under-30-asia-2020-the-startups-leveraging-ai-and-machine-learning-to-transform-businesses.md",
      "title": "30 Under 30 Asia 2020: The Startups Leveraging AI And Machine Learning To Transform Businesses",
      "excerpt": "Hyunsoo Kim, cofounder of Superb AI, has been selected as the featured honoree for the Enterprise Technology category of this year’s Forbes 30 Under 30 Asia list, leading a pack of several fellow honorees who founded startups based on AI.",
      "heat": 92,
      "tags": null,
      "type": "article",
      "webUrl": "https://www.forbes.com/sites/johnkang/2020/04/01/30-under-30-asia-2020-the-startups-leveraging-ai-and-machine-learning-to-transform-businesses/",
      "ampWebUrl": "https://www.forbes.com/sites/johnkang/2020/04/01/30-under-30-asia-2020-the-startups-leveraging-ai-and-machine-learning-to-transform-businesses/amp/",
      "cdnAmpWebUrl": "https://www-forbes-com.cdn.ampproject.org/c/s/www.forbes.com/sites/johnkang/2020/04/01/30-under-30-asia-2020-the-startups-leveraging-ai-and-machine-learning-to-transform-businesses/amp/",
      "publishedDateTime": "2020-04-01T14:42:00-07:00",
      "updatedDateTime": null,
      "provider": {
        "name": "Forbes",
        "domain": "forbes.com",
        "images": [
          {
            "url": "https://insideout.app/ai/assets/images/organizations/forbes.com-50x50.jpg",
            "width": 50,
            "height": 50,
            "title": null,
            "attribution": null
          }
        ],
        "publishers": null,
        "authors": null
      },
      "images": [
        {
          "url": "https://thumbor.forbes.com/thumbor/fit-in/1200x0/filters%3Aformat%28jpg%29/https%3A%2F%2Fspecials-images.forbesimg.com%2Fimageserve%2F5e709bc5e1e61700080f01bc%2F0x0.jpg",
          "width": 1200,
          "height": 800,
          "title": "30 Under 30 Asia 2020: The Startups Leveraging AI And Machine Learning To Transform Businesses",
          "attribution": null
        }
      ],
      "locale": "en-us",
      "categories": [
        "news"
      ],
      "topics": [
        "Machine Learning",
        "AI"
      ]
    },
    {
      "path": "_news/2020-04-01-ai-supported-sales-reps-how-to-make-it-work.md",
      "title": "AI-Supported Sales Reps: How To Make It Work",
      "excerpt": "AI can help salespeople do more of what they do best, but most efforts to enable reps with AI fail. Here's why, and how to make it work for your organization.",
      "heat": 87,
      "tags": null,
      "type": "article",
      "webUrl": "https://www.forbes.com/sites/arunshastri/2020/04/01/ai-supported-sales-reps-how-to-make-it-work/",
      "ampWebUrl": "https://www.forbes.com/sites/arunshastri/2020/04/01/ai-supported-sales-reps-how-to-make-it-work/amp/",
      "cdnAmpWebUrl": "https://www-forbes-com.cdn.ampproject.org/c/s/www.forbes.com/sites/arunshastri/2020/04/01/ai-supported-sales-reps-how-to-make-it-work/amp/",
      "publishedDateTime": "2020-04-01T13:36:00-07:00",
      "updatedDateTime": null,
      "provider": {
        "name": "Forbes",
        "domain": "forbes.com",
        "images": [
          {
            "url": "https://insideout.app/ai/assets/images/organizations/forbes.com-50x50.jpg",
            "width": 50,
            "height": 50,
            "title": null,
            "attribution": null
          }
        ],
        "publishers": null,
        "authors": null
      },
      "images": [
        {
          "url": "https://thumbor.forbes.com/thumbor/fit-in/1200x0/filters%3Aformat%28jpg%29/https%3A%2F%2Fspecials-images.forbesimg.com%2Fimageserve%2F1132912559%2F0x0.jpg",
          "width": 1200,
          "height": 720,
          "title": "AI-Supported Sales Reps: How To Make It Work",
          "attribution": null
        }
      ],
      "locale": "en-us",
      "categories": [
        "news"
      ],
      "topics": [
        "AI"
      ]
    },
    {
      "path": "_news/2020-04-01-an-interview-with-microsoft-president-brad-smith.md",
      "title": "An interview with Microsoft President Brad Smith",
      "excerpt": "The post An interview with Microsoft President Brad Smith appeared first on The AI Blog.\n",
      "heat": 89,
      "tags": null,
      "type": "article",
      "webUrl": "https://www.microsoft.com/en-us/research/blog/an-interview-with-microsoft-president-brad-smith/",
      "ampWebUrl": null,
      "cdnAmpWebUrl": null,
      "publishedDateTime": "2020-04-01T13:06:20-07:00",
      "updatedDateTime": null,
      "provider": {
        "name": "Microsoft",
        "domain": "microsoft.com",
        "images": [
          {
            "url": "https://insideout.app/ai/assets/images/organizations/microsoft.com-50x50.jpg",
            "width": 50,
            "height": 50,
            "title": null,
            "attribution": null
          }
        ],
        "publishers": null,
        "authors": null
      },
      "images": [
        {
          "url": "https://www.microsoft.com/en-us/research/uploads/prod/2020/03/Research_Podcast_Smith_Social_1200x627.png",
          "width": 1200,
          "height": 627,
          "title": "An interview with Microsoft President Brad Smith",
          "attribution": null
        }
      ],
      "locale": "en-us",
      "categories": [
        "news"
      ],
      "topics": [
        "AI",
        "Microsoft AI"
      ]
    },
    {
      "path": "_news/2020-04-01-deepminds-new-ai-can-beat-humans-at-57-atari-games.md",
      "title": "DeepMind’s new AI can beat humans at 57 Atari games",
      "excerpt": "Google subsidiary DeepMind has unveiled an AI called Agent57 that can beat the average human at 57 classic Atari games. The system achieved this feat using deep reinforcement learning, a machine learning technique that helps an AI improve its decisions by trying out different approaches and learning from its mistakes. DeepMind used the same ...",
      "heat": 124,
      "tags": null,
      "type": "article",
      "webUrl": "https://thenextweb.com/neural/2020/04/01/deepminds-new-agent57-ai-can-beat-humans-at-57-atari-games/",
      "ampWebUrl": "https://thenextweb.com/neural/2020/04/01/deepminds-new-agent57-ai-can-beat-humans-at-57-atari-games/amp/",
      "cdnAmpWebUrl": "https://thenextweb-com.cdn.ampproject.org/c/s/thenextweb.com/neural/2020/04/01/deepminds-new-agent57-ai-can-beat-humans-at-57-atari-games/amp/",
      "publishedDateTime": "2020-04-01T10:39:00-07:00",
      "updatedDateTime": null,
      "provider": {
        "name": "The Next Web",
        "domain": "thenextweb.com",
        "images": [
          {
            "url": "https://insideout.app/ai/assets/images/organizations/thenextweb.com-50x50.jpg",
            "width": 50,
            "height": 50,
            "title": null,
            "attribution": null
          }
        ],
        "publishers": null,
        "authors": null
      },
      "images": [
        {
          "url": "https://cdn0.tnwcdn.com/wp-content/blogs.dir/1/files/2020/04/Untitled-design46-796x417.png",
          "width": 796,
          "height": 417,
          "title": "DeepMind’s new AI can beat humans at 57 Atari games",
          "attribution": null
        }
      ],
      "locale": "en-us",
      "categories": [
        "news"
      ],
      "topics": [
        "AI",
        "Google AI"
      ]
    },
    {
      "path": "_news/2020-04-01-deepminds-ai-learned-how-to-play-every-atari-game.md",
      "title": "DeepMind's AI learned how to play every Atari game",
      "excerpt": "Google-owned artificial intelligence firm DeepMind developed an AI system that can play all 57 video games and beat human averages, according to a research paper published this week. The AI, called Agent57,",
      "heat": 114,
      "tags": null,
      "type": "article",
      "webUrl": "https://www.cnet.com/news/deepminds-ai-learned-how-to-play-every-atari-game/",
      "ampWebUrl": "https://www.cnet.com/google-amp/news/deepminds-ai-learned-how-to-play-every-atari-game/",
      "cdnAmpWebUrl": "https://www-cnet-com.cdn.ampproject.org/c/s/www.cnet.com/google-amp/news/deepminds-ai-learned-how-to-play-every-atari-game/",
      "publishedDateTime": "2020-04-01T10:16:00-07:00",
      "updatedDateTime": null,
      "provider": {
        "name": "CNET",
        "domain": "cnet.com",
        "images": [
          {
            "url": "https://insideout.app/ai/assets/images/organizations/cnet.com-50x50.jpg",
            "width": 50,
            "height": 50,
            "title": null,
            "attribution": null
          }
        ],
        "publishers": null,
        "authors": null
      },
      "images": [
        {
          "url": "https://cnet2.cbsistatic.com/img/4GAXIulyS7cubuKb6mk5aqZ-qbI=/756x567/2017/07/27/3de74c24-095d-4c7e-9d5d-fb69ee27aaff/atari-flashback-8-gold-82.jpg",
          "width": 756,
          "height": 567,
          "title": "DeepMind's AI learned how to play every Atari game",
          "attribution": null
        }
      ],
      "locale": "en-us",
      "categories": [
        "news"
      ],
      "topics": [
        "Google AI",
        "AI"
      ]
    },
    {
      "path": "_news/2020-04-01-alphabets-deepmind-ai-is-better-than-you-at-atari-games.md",
      "title": "Alphabet’s DeepMind AI is better than you at Atari games",
      "excerpt": "Having AI agents learn how to play simple video games is an ideal way to test their effectiveness, thanks to the ability to measure success via a score. Alphabet's DeepMind designated 57 particular Atari games to serve as a litmus test for its AI, and established a benchmark for the skills of an average human player. The company's latest system ...",
      "heat": 124,
      "tags": null,
      "type": "article",
      "webUrl": "https://www.engadget.com/2020-04-01-deepmind-agent57-ai-atari.html",
      "ampWebUrl": "https://www.engadget.com/amp/2020-04-01-deepmind-agent57-ai-atari.html",
      "cdnAmpWebUrl": "https://www-engadget-com.cdn.ampproject.org/c/s/www.engadget.com/amp/2020-04-01-deepmind-agent57-ai-atari.html",
      "publishedDateTime": "2020-04-01T09:47:00-07:00",
      "updatedDateTime": null,
      "provider": {
        "name": "Engadget",
        "domain": "engadget.com",
        "images": [
          {
            "url": "https://insideout.app/ai/assets/images/organizations/engadget.com-50x50.jpg",
            "width": 50,
            "height": 50,
            "title": null,
            "attribution": null
          }
        ],
        "publishers": null,
        "authors": null
      },
      "images": [
        {
          "url": "https://o.aolcdn.com/images/dims?thumbnail=600%2C350&quality=80&image_uri=https%3A%2F%2Fo.aolcdn.com%2Fimages%2Fdims%3Fcrop%3D5600%252C3035%252C0%252C701%26quality%3D85%26format%3Djpg%26resize%3D1600%252C867%26image_uri%3Dhttps%253A%252F%252Fs.yimg.com%252Fos%252Fcreatr-images%252F2020-04%252F99e3f5c0-742f-11ea-b93f-3ab31fad626d%26client%3Da1acac3e1b3290917d92%26signature%3D50e87b16d59bff72a11f5cd3c3bba0eaaac088ba&client=amp-blogside-v2&signature=11dace15f5dff7bbf1c1c07bb67f847e04c238e5",
          "width": 600,
          "height": 350,
          "title": "Alphabet’s DeepMind AI is better than you at Atari games",
          "attribution": null
        }
      ],
      "locale": "en-us",
      "categories": [
        "news"
      ],
      "topics": [
        "Google AI",
        "AI"
      ]
    },
    {
      "path": "_news/2020-04-01-ai-reimagines-the-great-british-bakeoff-as-a-very-weird-acid-trip.md",
      "title": "AI reimagines The Great British Bakeoff as a very weird acid trip",
      "excerpt": "Hungry for some hoverbread or void cake? A neural net shows off its idea of a perfectly terrifying baking show I wish really existed. The Great British Bake Off -- rebranded for Americans as on Netflix -- features amateur bakers competing to make the best cakes,",
      "heat": 87,
      "tags": null,
      "type": "article",
      "webUrl": "https://www.cnet.com/news/ai-reimagines-the-great-british-bakeoff-as-a-very-weird-acid-trip/",
      "ampWebUrl": "https://www.cnet.com/google-amp/news/ai-reimagines-the-great-british-bakeoff-as-a-very-weird-acid-trip/",
      "cdnAmpWebUrl": "https://www-cnet-com.cdn.ampproject.org/c/s/www.cnet.com/google-amp/news/ai-reimagines-the-great-british-bakeoff-as-a-very-weird-acid-trip/",
      "publishedDateTime": "2020-04-01T09:45:00-07:00",
      "updatedDateTime": null,
      "provider": {
        "name": "CNET",
        "domain": "cnet.com",
        "images": [
          {
            "url": "https://insideout.app/ai/assets/images/organizations/cnet.com-50x50.jpg",
            "width": 50,
            "height": 50,
            "title": null,
            "attribution": null
          }
        ],
        "publishers": null,
        "authors": null
      },
      "images": [
        {
          "url": "https://cnet4.cbsistatic.com/img/_NFXuYENEEJ7hMHCIZXmzRbR3gg=/2020/04/01/e09279d1-c2fd-4138-b8e5-ea9d977dd720/twitter-in-stream-wide-bakeoff2.jpg",
          "width": 1638,
          "height": 819,
          "title": "AI reimagines The Great British Bakeoff as a very weird acid trip",
          "attribution": null
        }
      ],
      "locale": "en-us",
      "categories": [
        "news"
      ],
      "topics": [
        "AI"
      ]
    },
    {
      "path": "_news/2020-04-01-is-this-ai-powered-mirror-gym-the-future-of-home-exercise.md",
      "title": "Is this AI-powered 'mirror gym' the future of home exercise?",
      "excerpt": "That same year, entrepreneur Aly Orady launched Tonal, an AI-powered wall-mounted screen that focuses more on strength training. It features an exercise bench and resistance system that uses electromagnetism to simulate weight machines. This month, entrepreneur Trent Ward and designer Yves Behar are unveiling their sleek design for a mirror ...",
      "heat": 87,
      "tags": null,
      "type": "article",
      "webUrl": "https://us.cnn.com/style/article/yves-behar-home-gym-forme-wellness/index.html",
      "ampWebUrl": "https://www.cnn.com/style/amp/yves-behar-home-gym-forme-wellness/index.html",
      "cdnAmpWebUrl": "https://www-cnn-com.cdn.ampproject.org/c/s/www.cnn.com/style/amp/yves-behar-home-gym-forme-wellness/index.html",
      "publishedDateTime": "2020-04-01T09:33:00-07:00",
      "updatedDateTime": null,
      "provider": {
        "name": "CNN",
        "domain": "cnn.com",
        "images": [
          {
            "url": "https://insideout.app/ai/assets/images/organizations/cnn.com-50x50.jpg",
            "width": 50,
            "height": 50,
            "title": null,
            "attribution": null
          }
        ],
        "publishers": null,
        "authors": null
      },
      "images": [
        {
          "url": "http://cdn.cnn.com/cnnnext/dam/assets/200401103641-05-yves-behar-super-tease.jpg",
          "width": 1100,
          "height": 619,
          "title": "Is this AI-powered 'mirror gym' the future of home exercise?",
          "attribution": null
        }
      ],
      "locale": "en-us",
      "categories": [
        "news"
      ],
      "topics": [
        "AI"
      ]
    },
    {
      "path": "_news/2020-04-01-microsofts-mahjong-winning-ai-could-lead-to-sophisticated-finance-market-prediction-systems.md",
      "title": "Microsoft’s Mahjong-winning AI could lead to sophisticated finance market prediction systems",
      "excerpt": "Last August, Microsoft Research Asia detailed an AI system dubbed Super Phoenix (Suphx for short) that could defeat Mahjong players after learning from only 5,000 matches. A revised preprint paper out this week delves a bit deeper, revealing that Suphx — whose performance improved with additional training — is now rated above 99.99% of all ...",
      "heat": 76,
      "tags": null,
      "type": "article",
      "webUrl": "https://venturebeat.com/2020/04/01/microsofts-mahjong-winning-ai-could-lead-to-sophisticated-finance-market-prediction-systems/",
      "ampWebUrl": "https://venturebeat.com/2020/04/01/microsofts-mahjong-winning-ai-could-lead-to-sophisticated-finance-market-prediction-systems/amp/",
      "cdnAmpWebUrl": "https://venturebeat-com.cdn.ampproject.org/c/s/venturebeat.com/2020/04/01/microsofts-mahjong-winning-ai-could-lead-to-sophisticated-finance-market-prediction-systems/amp/",
      "publishedDateTime": "2020-04-01T09:16:00-07:00",
      "updatedDateTime": null,
      "provider": {
        "name": "VentureBeat",
        "domain": "venturebeat.com",
        "images": [
          {
            "url": "https://insideout.app/ai/assets/images/organizations/venturebeat.com-50x50.jpg",
            "width": 50,
            "height": 50,
            "title": null,
            "attribution": null
          }
        ],
        "publishers": null,
        "authors": null
      },
      "images": [
        {
          "url": "https://venturebeat.com/wp-content/uploads/2019/11/microsoft-1-e1580261336710.jpg?fit=1200%2C573&strip=all",
          "width": 1200,
          "height": 573,
          "title": "Microsoft’s Mahjong-winning AI could lead to sophisticated finance market prediction systems",
          "attribution": null
        }
      ],
      "locale": "en-us",
      "categories": [
        "news"
      ],
      "topics": [
        "AI"
      ]
    },
    {
      "path": "_news/2020-04-01-terrifying-things-happen-when-an-ai-generates-fake-faces-synced-to-music.md",
      "title": "Terrifying Things Happen When an AI Generates Fake Faces Synced to Music",
      "excerpt": "We’re still trying to figure out the best applications for neural networks, machine learning, and all the recent advancements in artificial intelligence. Amongst all the practical research being conducted, there’s also lots of frivolous experimentation being done with results that walk the line between fascinating and terrifying. Automated ...",
      "heat": 86,
      "tags": null,
      "type": "article",
      "webUrl": "https://gizmodo.com/terrifying-things-happen-when-an-ai-generates-fake-face-1842592456",
      "ampWebUrl": "https://gizmodo.com/terrifying-things-happen-when-an-ai-generates-fake-face-1842592456/amp",
      "cdnAmpWebUrl": "https://gizmodo-com.cdn.ampproject.org/c/s/gizmodo.com/terrifying-things-happen-when-an-ai-generates-fake-face-1842592456/amp",
      "publishedDateTime": "2020-04-01T07:49:00-07:00",
      "updatedDateTime": null,
      "provider": {
        "name": "Gizmodo",
        "domain": "gizmodo.com",
        "images": [
          {
            "url": "https://insideout.app/ai/assets/images/organizations/gizmodo.com-50x50.jpg",
            "width": 50,
            "height": 50,
            "title": null,
            "attribution": null
          }
        ],
        "publishers": null,
        "authors": null
      },
      "images": [
        {
          "url": "https://i.kinja-img.com/gawker-media/image/upload/c_scale,f_auto,fl_progressive,q_80,w_800/lmmxqkwklbkuqyzfjsbv.jpg",
          "width": 800,
          "height": 450,
          "title": "Terrifying Things Happen When an AI Generates Fake Faces Synced to Music",
          "attribution": null
        }
      ],
      "locale": "en-us",
      "categories": [
        "news"
      ],
      "topics": [
        "AI"
      ]
    },
    {
      "path": "_news/2020-04-01-nokia-stirs-telco-space-with-5g-backed-automated-operations.md",
      "title": "Nokia Stirs Telco Space With 5G-Backed Automated Operations",
      "excerpt": "Nokia Corporation NOK recently unveiled an out-and-out AI-backed service offering that helps communication service providers (CSPs) to support future network evolution, and optimize enterprise and cloud services on a global scale.",
      "heat": 74,
      "tags": null,
      "type": "article",
      "webUrl": "https://www.nasdaq.com/articles/nokia-stirs-telco-space-with-5g-backed-automated-operations-2020-04-01",
      "ampWebUrl": "https://www.nasdaq.com/articles/nokia-stirs-telco-space-with-5g-backed-automated-operations-2020-04-01?amp",
      "cdnAmpWebUrl": "https://www-nasdaq-com.cdn.ampproject.org/c/s/www.nasdaq.com/articles/nokia-stirs-telco-space-with-5g-backed-automated-operations-2020-04-01?amp",
      "publishedDateTime": "2020-04-01T07:08:00-07:00",
      "updatedDateTime": null,
      "provider": {
        "name": "Nasdaq",
        "domain": "nasdaq.com",
        "images": null,
        "publishers": null,
        "authors": null
      },
      "images": [
        {
          "url": "https://www.nasdaq.com/sites/acquia.prod/files/2019-05/0902-Q19%20Total%20Markets%20photos%20and%20gif_CC8.jpg?1421883099",
          "width": 1024,
          "height": 512,
          "title": "Nokia Stirs Telco Space With 5G-Backed Automated Operations",
          "attribution": null
        }
      ],
      "locale": "en-us",
      "categories": [
        "news"
      ],
      "topics": [
        "Microsoft AI",
        "AI"
      ]
    },
    {
      "path": "_news/2020-04-01-ai-for-business-whats-going-wrong-and-how-to-get-it-right.md",
      "title": "AI for business: What's going wrong, and how to get it right",
      "excerpt": "Despite years of hype (and plenty of worries) about the all-conquering power of Artificial Intelligence (AI), there still remains a significant gap between the promise of AI and its reality for business. Tech firms have pitched AI's capabilities for years, but for most organisations, the benefits of AI remain elusive. It's hard to gauge the ...",
      "heat": 88,
      "tags": null,
      "type": "article",
      "webUrl": "https://www.zdnet.com/article/ai-for-business-whats-going-wrong-and-how-to-get-it-right/",
      "ampWebUrl": "https://www.zdnet.com/google-amp/article/ai-for-business-whats-going-wrong-and-how-to-get-it-right/",
      "cdnAmpWebUrl": "https://www-zdnet-com.cdn.ampproject.org/c/s/www.zdnet.com/google-amp/article/ai-for-business-whats-going-wrong-and-how-to-get-it-right/",
      "publishedDateTime": "2020-04-01T06:31:00-07:00",
      "updatedDateTime": null,
      "provider": {
        "name": "ZDNet",
        "domain": "zdnet.com",
        "images": [
          {
            "url": "https://insideout.app/ai/assets/images/organizations/zdnet.com-50x50.jpg",
            "width": 50,
            "height": 50,
            "title": null,
            "attribution": null
          }
        ],
        "publishers": null,
        "authors": null
      },
      "images": [
        {
          "url": "https://zdnet3.cbsistatic.com/hub/i/2020/03/11/29d9c9c7-9b3e-4238-850d-13abf03f6a22/1-gartner-orgas-want-to-deploy-more-ai.png",
          "width": 1200,
          "height": 626,
          "title": "AI for business: What's going wrong, and how to get it right",
          "attribution": null
        }
      ],
      "locale": "en-us",
      "categories": [
        "news"
      ],
      "topics": [
        "AI"
      ]
    },
    {
      "path": "_news/2020-04-01-cio-jury-83-of-tech-leaders-have-no-policy-for-ethically-using-ai.md",
      "title": "CIO Jury: 83% of tech leaders have no policy for ethically using AI",
      "excerpt": "Read More When asked, \"Does your company have a policy for ethically using AI or machine learning?\" 10 out of 12 tech leaders said no, while just two said yes. That means only 17% of tech leaders in TechRepublic's informal poll have an ethics policy in place for AI and ML. Exactly 12 months ago, TechRepublic asked the same question to its CIO ...",
      "heat": 104,
      "tags": null,
      "type": "article",
      "webUrl": "https://www.zdnet.com/article/cio-jury-83-of-tech-leaders-have-no-policy-for-ethically-using-ai/",
      "ampWebUrl": "https://www.zdnet.com/google-amp/article/cio-jury-83-of-tech-leaders-have-no-policy-for-ethically-using-ai/",
      "cdnAmpWebUrl": "https://www-zdnet-com.cdn.ampproject.org/c/s/www.zdnet.com/google-amp/article/cio-jury-83-of-tech-leaders-have-no-policy-for-ethically-using-ai/",
      "publishedDateTime": "2020-04-01T06:26:00-07:00",
      "updatedDateTime": null,
      "provider": {
        "name": "ZDNet",
        "domain": "zdnet.com",
        "images": [
          {
            "url": "https://insideout.app/ai/assets/images/organizations/zdnet.com-50x50.jpg",
            "width": 50,
            "height": 50,
            "title": null,
            "attribution": null
          }
        ],
        "publishers": null,
        "authors": null
      },
      "images": [
        {
          "url": "https://zdnet1.cbsistatic.com/hub/i/r/2020/03/04/1f124c5b-e8c9-4e32-bd55-0b43c2ebaad2/thumbnail/1200x675/e2dadb62383d012b4fc239d2dd0ac8e1/thumb.jpg",
          "width": 1200,
          "height": 675,
          "title": "CIO Jury: 83% of tech leaders have no policy for ethically using AI",
          "attribution": null
        }
      ],
      "locale": "en-us",
      "categories": [
        "news"
      ],
      "topics": [
        "AI Ethics",
        "AI"
      ]
    },
    {
      "path": "_news/2020-04-01-developers-its-time-to-brush-up-on-your-philosophy-ethical-ai-is-the-big-new-thing-in-tech.md",
      "title": "Developers - it's time to brush up on your philosophy: Ethical AI is the big new thing in tech",
      "excerpt": "What's more: algorithmic bias is only one side of the problem: the 'ethics of AI' picture is indeed a multifaceted one. To mitigate the unwelcome consequences of AI systems, governments around the world have been working on drafts, guidelines and frameworks designed to inform developers and help them come up with algorithms that are respectful ...",
      "heat": 94,
      "tags": null,
      "type": "article",
      "webUrl": "https://www.zdnet.com/article/developers-its-time-to-brush-up-on-your-philosophy-ethical-ai-is-the-big-new-thing-in-tech/",
      "ampWebUrl": "https://www.zdnet.com/google-amp/article/developers-its-time-to-brush-up-on-your-philosophy-ethical-ai-is-the-big-new-thing-in-tech/",
      "cdnAmpWebUrl": "https://www-zdnet-com.cdn.ampproject.org/c/s/www.zdnet.com/google-amp/article/developers-its-time-to-brush-up-on-your-philosophy-ethical-ai-is-the-big-new-thing-in-tech/",
      "publishedDateTime": "2020-04-01T06:21:00-07:00",
      "updatedDateTime": null,
      "provider": {
        "name": "ZDNet",
        "domain": "zdnet.com",
        "images": [
          {
            "url": "https://insideout.app/ai/assets/images/organizations/zdnet.com-50x50.jpg",
            "width": 50,
            "height": 50,
            "title": null,
            "attribution": null
          }
        ],
        "publishers": null,
        "authors": null
      },
      "images": [
        {
          "url": "https://zdnet3.cbsistatic.com/hub/i/r/2019/11/06/a1e2b9a4-9330-4565-8e20-f6fb00e3d1a9/thumbnail/1200x675/251d1466033401dd47e80d969b17de3e/20191106-daphne-karen-war.png",
          "width": 1200,
          "height": 675,
          "title": "Developers - it's time to brush up on your philosophy: Ethical AI is the big new thing in tech",
          "attribution": null
        }
      ],
      "locale": "en-us",
      "categories": [
        "news"
      ],
      "topics": [
        "AI Ethics",
        "AI",
        "Computer Vision"
      ]
    },
    {
      "path": "_news/2020-04-01-ai-vs-your-career-what-artificial-intelligence-will-really-do-to-the-future-of-work.md",
      "title": "AI vs your career? What artificial intelligence will really do to the future of work",
      "excerpt": "In a similar vein, Gartner recently suggested that HR departments start including a section dedicated to \"robot resources\", to better manage employees as they start working alongside robotic colleagues. \"Getting an AI to collaborate with humans in the ways that we collaborate with others at work, every day, is incredibly hard,\" said McDonald.",
      "heat": 99,
      "tags": null,
      "type": "article",
      "webUrl": "https://www.zdnet.com/article/ai-vs-your-career-what-artificial-intelligence-will-really-do-to-the-future-of-work/",
      "ampWebUrl": "https://www.zdnet.com/google-amp/article/ai-vs-your-career-what-artificial-intelligence-will-really-do-to-the-future-of-work/",
      "cdnAmpWebUrl": "https://www-zdnet-com.cdn.ampproject.org/c/s/www.zdnet.com/google-amp/article/ai-vs-your-career-what-artificial-intelligence-will-really-do-to-the-future-of-work/",
      "publishedDateTime": "2020-04-01T06:19:00-07:00",
      "updatedDateTime": null,
      "provider": {
        "name": "ZDNet",
        "domain": "zdnet.com",
        "images": [
          {
            "url": "https://insideout.app/ai/assets/images/organizations/zdnet.com-50x50.jpg",
            "width": 50,
            "height": 50,
            "title": null,
            "attribution": null
          }
        ],
        "publishers": null,
        "authors": null
      },
      "images": [
        {
          "url": "https://zdnet2.cbsistatic.com/hub/i/r/2019/12/04/657acd78-13b6-4989-8ecf-673fb8d38d60/thumbnail/1200x675/ab7a6c328b2d02457d5800ac6d49ad7f/thumb.jpg",
          "width": 1200,
          "height": 675,
          "title": "AI vs your career? What artificial intelligence will really do to the future of work",
          "attribution": null
        }
      ],
      "locale": "en-us",
      "categories": [
        "news"
      ],
      "topics": [
        "AI in Robotics",
        "AI",
        "IBM AI"
      ]
    },
    {
      "path": "_news/2020-04-01-ai-and-ml-move-into-financial-services.md",
      "title": "AI and ML move into financial services",
      "excerpt": "\"At the highest level, by utilizing machine learning, financial services organizations can pinpoint their most effective offerings, change how they attract and keep customers by identifying patterns in their behaviors/interactions with the institution, and [create] opportunities for engagement beyond just financial services.\" Machine learning ...",
      "heat": 91,
      "tags": null,
      "type": "article",
      "webUrl": "https://www.zdnet.com/article/ai-and-ml-move-into-financial-services/",
      "ampWebUrl": "https://www.zdnet.com/google-amp/article/ai-and-ml-move-into-financial-services/",
      "cdnAmpWebUrl": "https://www-zdnet-com.cdn.ampproject.org/c/s/www.zdnet.com/google-amp/article/ai-and-ml-move-into-financial-services/",
      "publishedDateTime": "2020-04-01T06:17:00-07:00",
      "updatedDateTime": null,
      "provider": {
        "name": "ZDNet",
        "domain": "zdnet.com",
        "images": [
          {
            "url": "https://insideout.app/ai/assets/images/organizations/zdnet.com-50x50.jpg",
            "width": 50,
            "height": 50,
            "title": null,
            "attribution": null
          }
        ],
        "publishers": null,
        "authors": null
      },
      "images": [
        {
          "url": "https://zdnet2.cbsistatic.com/hub/i/r/2020/03/27/a57f5328-54c9-4429-a05f-165bfe54dfed/thumbnail/1200x675/cff661fe04c50b47434ccd8665b9dfc3/mastercard-keeping-humans-in-the-loop-of-5e7d26ca80c7260bd0dee6fd-1-mar-27-2020-24-01-06-poster.jpg",
          "width": 1200,
          "height": 675,
          "title": "AI and ML move into financial services",
          "attribution": null
        }
      ],
      "locale": "en-us",
      "categories": [
        "news"
      ],
      "topics": [
        "AI in Finance",
        "AI",
        "AI Ethics"
      ]
    },
    {
      "path": "_news/2020-04-01-healthcare-and-artificial-intelligence-how-databricks-uses-apache-spark-to-analyze-huge-data-sets.md",
      "title": "Healthcare and artificial intelligence: How Databricks uses Apache Spark to analyze huge data sets",
      "excerpt": "There is no shortage of big data sets in the healthcare world, encompassing everything from chest X-rays to drug research. Startups and established companies alike are both using artificial intelligence (AI) and machine learning to analyze these data sets and use the results to guide business strategy and treatment plans. Special Feature ...",
      "heat": 90,
      "tags": null,
      "type": "article",
      "webUrl": "https://www.zdnet.com/article/healthcare-and-artificial-intelligence-how-databricks-uses-apache-spark-to-analyze-huge-data-sets/",
      "ampWebUrl": "https://www.zdnet.com/google-amp/article/healthcare-and-artificial-intelligence-how-databricks-uses-apache-spark-to-analyze-huge-data-sets/",
      "cdnAmpWebUrl": "https://www-zdnet-com.cdn.ampproject.org/c/s/www.zdnet.com/google-amp/article/healthcare-and-artificial-intelligence-how-databricks-uses-apache-spark-to-analyze-huge-data-sets/",
      "publishedDateTime": "2020-04-01T06:15:00-07:00",
      "updatedDateTime": null,
      "provider": {
        "name": "ZDNet",
        "domain": "zdnet.com",
        "images": [
          {
            "url": "https://insideout.app/ai/assets/images/organizations/zdnet.com-50x50.jpg",
            "width": 50,
            "height": 50,
            "title": null,
            "attribution": null
          }
        ],
        "publishers": null,
        "authors": null
      },
      "images": [
        {
          "url": "https://zdnet2.cbsistatic.com/hub/i/r/2020/03/12/dd98591c-0dd3-4ca8-b9b9-a86a1a885ead/thumbnail/1200x675/eb84aa5cfc1c259d5633e76710557363/ibm-tests-the-use-of-artificial-intellig-5e69776e710b2800019c9e04-1-mar-12-2020-2-28-12-poster.jpg",
          "width": 1200,
          "height": 675,
          "title": "Healthcare and artificial intelligence: How Databricks uses Apache Spark to analyze huge data sets",
          "attribution": null
        }
      ],
      "locale": "en-us",
      "categories": [
        "news"
      ],
      "topics": [
        "AI in Healthcare",
        "AI"
      ]
    },
    {
      "path": "_news/2020-04-01-how-artificial-intelligence-and-machine-learning-are-used-in-hiring-and-recruiting.md",
      "title": "How artificial intelligence and machine learning are used in hiring and recruiting",
      "excerpt": "The hiring process has come a long way from the days of paper resumés and cold calls via landline. Online job sites are now staples in talent acquisition, but artificial intelligence (AI) and machine learning are elevating the recruiting and hiring landscape. Special Feature: Managing AI and ML in the Enterprise This ebook, based on the ...",
      "heat": 98,
      "tags": null,
      "type": "article",
      "webUrl": "https://www.zdnet.com/article/how-artificial-intelligence-and-machine-learning-are-used-in-hiring-and-recruiting/",
      "ampWebUrl": "https://www.zdnet.com/google-amp/article/how-artificial-intelligence-and-machine-learning-are-used-in-hiring-and-recruiting/",
      "cdnAmpWebUrl": "https://www-zdnet-com.cdn.ampproject.org/c/s/www.zdnet.com/google-amp/article/how-artificial-intelligence-and-machine-learning-are-used-in-hiring-and-recruiting/",
      "publishedDateTime": "2020-04-01T06:13:00-07:00",
      "updatedDateTime": null,
      "provider": {
        "name": "ZDNet",
        "domain": "zdnet.com",
        "images": [
          {
            "url": "https://insideout.app/ai/assets/images/organizations/zdnet.com-50x50.jpg",
            "width": 50,
            "height": 50,
            "title": null,
            "attribution": null
          }
        ],
        "publishers": null,
        "authors": null
      },
      "images": [
        {
          "url": "https://zdnet4.cbsistatic.com/hub/i/r/2020/02/13/4e4cd8eb-2afd-473d-975b-c13946cf39b2/thumbnail/1200x675/dad81bd63119e6cc97708778a9d27876/thumb.jpg",
          "width": 1200,
          "height": 675,
          "title": "How artificial intelligence and machine learning are used in hiring and recruiting",
          "attribution": null
        }
      ],
      "locale": "en-us",
      "categories": [
        "news"
      ],
      "topics": [
        "Machine Learning",
        "AI"
      ]
    },
    {
      "path": "_news/2020-04-01-shanghai-judicial-courts-start-to-replace-clerks-with-ai-assistants.md",
      "title": "Shanghai judicial courts start to replace clerks with AI assistants",
      "excerpt": "The judicial system in China is set for a hi-tech shake-up, as artificial intelligence (AI) will soon automate the traditional job performed by clerks in courtrooms across the country. That initiative started on Wednesday under a pilot programme in Shanghai, where 10 courts replaced clerks with AI assistants to transcribe case notes ...",
      "heat": 87,
      "tags": null,
      "type": "article",
      "webUrl": "https://www.scmp.com/tech/innovation/article/3077979/shanghai-judicial-courts-start-replace-clerks-ai-assistants",
      "ampWebUrl": "https://amp.scmp.com/tech/innovation/article/3077979/shanghai-judicial-courts-start-replace-clerks-ai-assistants",
      "cdnAmpWebUrl": "https://amp-scmp-com.cdn.ampproject.org/c/s/amp.scmp.com/tech/innovation/article/3077979/shanghai-judicial-courts-start-replace-clerks-ai-assistants",
      "publishedDateTime": "2020-04-01T05:00:00-07:00",
      "updatedDateTime": null,
      "provider": {
        "name": "South China Morning Post",
        "domain": "scmp.com",
        "images": [
          {
            "url": "https://insideout.app/ai/assets/images/organizations/scmp.com-50x50.jpg",
            "width": 50,
            "height": 50,
            "title": null,
            "attribution": null
          }
        ],
        "publishers": null,
        "authors": null
      },
      "images": [
        {
          "url": "https://cdn.i-scmp.com/sites/default/files/styles/og_image_scmp_generic/public/d8/images/methode/2020/04/01/4a082aa2-73ef-11ea-ab8f-988daf8efd6f_image_hires_215024.JPG?itok=j8en0PIv&v=1585749033",
          "width": 1200,
          "height": 630,
          "title": "Shanghai judicial courts start to replace clerks with AI assistants",
          "attribution": null
        }
      ],
      "locale": "en-us",
      "categories": [
        "news"
      ],
      "topics": [
        "AI"
      ]
    },
    {
      "path": "_news/2020-04-01-actioning-individual-customer-context-with-artificial-intelligence.md",
      "title": "Actioning Individual Customer Context With Artificial Intelligence",
      "excerpt": "The current capabilities of ML and AI allow not only the complete context of the customer to be gathered instantly, but also to serve the experience most likely to drive customers lower down the funnel.",
      "heat": 87,
      "tags": null,
      "type": "article",
      "webUrl": "https://www.forbes.com/sites/forbesbusinesscouncil/2020/04/01/actioning-individual-customer-context-with-artificial-intelligence/",
      "ampWebUrl": "https://www.forbes.com/sites/forbesbusinesscouncil/2020/04/01/actioning-individual-customer-context-with-artificial-intelligence/amp/",
      "cdnAmpWebUrl": "https://www-forbes-com.cdn.ampproject.org/c/s/www.forbes.com/sites/forbesbusinesscouncil/2020/04/01/actioning-individual-customer-context-with-artificial-intelligence/amp/",
      "publishedDateTime": "2020-04-01T04:53:00-07:00",
      "updatedDateTime": null,
      "provider": {
        "name": "Forbes",
        "domain": "forbes.com",
        "images": [
          {
            "url": "https://insideout.app/ai/assets/images/organizations/forbes.com-50x50.jpg",
            "width": 50,
            "height": 50,
            "title": null,
            "attribution": null
          }
        ],
        "publishers": null,
        "authors": null
      },
      "images": [
        {
          "url": "https://thumbor.forbes.com/thumbor/fit-in/1200x0/filters%3Aformat%28jpg%29/https%3A%2F%2Fblogs-images.forbes.com%2Fforbesbusinesscouncil%2Ffiles%2F2020%2F04%2F158.jpg",
          "width": 640,
          "height": 640,
          "title": "Actioning Individual Customer Context With Artificial Intelligence",
          "attribution": null
        }
      ],
      "locale": "en-us",
      "categories": [
        "news"
      ],
      "topics": [
        "AI"
      ]
    },
    {
      "path": "_news/2020-04-01-ai-led-operations-a-way-for-enterprises-to-scale-with-foresight.md",
      "title": "AI-Led Operations: A Way For Enterprises To Scale With Foresight",
      "excerpt": "Things move quickly in business today. And organizations are increasingly using data to move their businesses forward. IT systems are generating a growing variety, velocity and volume of data. This both creates challenges and opens up new opportunities.",
      "heat": 89,
      "tags": null,
      "type": "article",
      "webUrl": "https://www.forbes.com/sites/forbestechcouncil/2020/04/01/ai-led-operations-a-way-for-enterprises-to-scale-with-foresight/",
      "ampWebUrl": "https://www.forbes.com/sites/forbestechcouncil/2020/04/01/ai-led-operations-a-way-for-enterprises-to-scale-with-foresight/amp/",
      "cdnAmpWebUrl": "https://www-forbes-com.cdn.ampproject.org/c/s/www.forbes.com/sites/forbestechcouncil/2020/04/01/ai-led-operations-a-way-for-enterprises-to-scale-with-foresight/amp/",
      "publishedDateTime": "2020-04-01T04:47:00-07:00",
      "updatedDateTime": null,
      "provider": {
        "name": "Forbes",
        "domain": "forbes.com",
        "images": [
          {
            "url": "https://insideout.app/ai/assets/images/organizations/forbes.com-50x50.jpg",
            "width": 50,
            "height": 50,
            "title": null,
            "attribution": null
          }
        ],
        "publishers": null,
        "authors": null
      },
      "images": [
        {
          "url": "https://thumbor.forbes.com/thumbor/fit-in/1200x0/filters%3Aformat%28jpg%29/https%3A%2F%2Fblogs-images.forbes.com%2Fforbestechcouncil%2Ffiles%2F2020%2F04%2Fa-49.jpg",
          "width": 640,
          "height": 640,
          "title": "AI-Led Operations: A Way For Enterprises To Scale With Foresight",
          "attribution": null
        }
      ],
      "locale": "en-us",
      "categories": [
        "news"
      ],
      "topics": [
        "AI",
        "Natural Language Processing"
      ]
    },
    {
      "path": "_news/2020-04-01-energy-saving-ai-is-coming-for-your-office-thermostat.md",
      "title": "Energy-Saving AI Is Coming for Your Office Thermostat",
      "excerpt": "If the workers got too hot or too cold, they could tap an app to say so. The AI would adapt, creating microclimates to reflect their feedback. But in time, Spanos expected, the workers wouldn't bother. His goal is to make the system forgettable. Lights will turn on as workers come and go; screens will flicker to life as they settle at their desks.",
      "heat": 89,
      "tags": null,
      "type": "article",
      "webUrl": "https://www.wired.com/story/energy-saving-ai-controls-lights-office-thermostat/",
      "ampWebUrl": "https://www.wired.com/story/energy-saving-ai-controls-lights-office-thermostat/amp",
      "cdnAmpWebUrl": "https://www-wired-com.cdn.ampproject.org/c/s/www.wired.com/story/energy-saving-ai-controls-lights-office-thermostat/amp",
      "publishedDateTime": "2020-04-01T03:00:00-07:00",
      "updatedDateTime": null,
      "provider": {
        "name": "Wired",
        "domain": "wired.com",
        "images": [
          {
            "url": "https://insideout.app/ai/assets/images/organizations/wired.com-50x50.jpg",
            "width": 50,
            "height": 50,
            "title": null,
            "attribution": null
          }
        ],
        "publishers": null,
        "authors": null
      },
      "images": [
        {
          "url": "https://media.vanityfair.com/photos/576c493744d93e6e4482bb21/master/pass/placeholder_the_scene.jpg",
          "width": 800,
          "height": 450,
          "title": "Energy-Saving AI Is Coming for Your Office Thermostat",
          "attribution": null
        }
      ],
      "locale": "en-us",
      "categories": [
        "news"
      ],
      "topics": [
        "AI",
        "Facebook AI"
      ]
    },
    {
      "path": "_news/2020-04-01-enterprise-artificial-intelligence-along-with-telehealth-and-teleconferences-can-help-in-fighting-covid-19.md",
      "title": "Enterprise Artificial Intelligence Along With Telehealth And Teleconferences Can Help In Fighting COVID-19",
      "excerpt": "enterprise artificial intelligence (AI) is not getting the same attention as teleconferencing and telehealth technologies. A massive shift to working from home to avoid spreading the virus means virtual collaboration companies like Zoom Video Communications are in the headlines. The same dynamic is playing out in healthcare as hospitals attempt ...",
      "heat": 71,
      "tags": null,
      "type": "article",
      "webUrl": "https://www.entrepreneur.com/article/348557",
      "ampWebUrl": "https://www.entrepreneur.com/amphtml/348557",
      "cdnAmpWebUrl": "https://www-entrepreneur-com.cdn.ampproject.org/c/s/www.entrepreneur.com/amphtml/348557",
      "publishedDateTime": "2020-04-01T02:06:00-07:00",
      "updatedDateTime": null,
      "provider": {
        "name": "Entrepreneur",
        "domain": "entrepreneur.com",
        "images": [
          {
            "url": "https://insideout.app/ai/assets/images/organizations/entrepreneur.com-50x50.jpg",
            "width": 50,
            "height": 50,
            "title": null,
            "attribution": null
          }
        ],
        "publishers": null,
        "authors": null
      },
      "images": [
        {
          "url": "https://assets.entrepreneur.com/content/3x2/2000/20190416142211-shutterstock-1168340332.jpeg?width=600&crop=16:9",
          "width": 600,
          "height": 338,
          "title": "Enterprise Artificial Intelligence Along With Telehealth And Teleconferences Can Help In Fighting COVID-19",
          "attribution": null
        }
      ],
      "locale": "en-us",
      "categories": [
        "news"
      ],
      "topics": [
        "AI in Healthcare",
        "AI"
      ]
    },
    {
      "path": "_news/2020-04-01-cordio-and-rambam-hospital-will-trial-ai-that-detects-coronavirus-cases-from-speech-samples.md",
      "title": "Cordio and Rambam Hospital will trial AI that detects coronavirus cases from speech samples",
      "excerpt": "Cordio Medical today announced that it will begin a clinical trial at Haifa’s Rambam Hospital on an app-based AI system that analyzes speech to diagnose and remotely monitor COVID-19 patients. Assuming it passes scientific muster, the tech could be used to help treat self-quarantined patients who are likely to have COVID-19 but who haven’t ...",
      "heat": 77,
      "tags": null,
      "type": "article",
      "webUrl": "https://venturebeat.com/2020/04/01/cordio-and-rambam-hospital-will-trial-ai-that-detects-coronavirus-cases-from-speech-samples/",
      "ampWebUrl": "https://venturebeat.com/2020/04/01/cordio-and-rambam-hospital-will-trial-ai-that-detects-coronavirus-cases-from-speech-samples/amp/",
      "cdnAmpWebUrl": "https://venturebeat-com.cdn.ampproject.org/c/s/venturebeat.com/2020/04/01/cordio-and-rambam-hospital-will-trial-ai-that-detects-coronavirus-cases-from-speech-samples/amp/",
      "publishedDateTime": "2020-04-01T02:03:00-07:00",
      "updatedDateTime": null,
      "provider": {
        "name": "VentureBeat",
        "domain": "venturebeat.com",
        "images": [
          {
            "url": "https://insideout.app/ai/assets/images/organizations/venturebeat.com-50x50.jpg",
            "width": 50,
            "height": 50,
            "title": null,
            "attribution": null
          }
        ],
        "publishers": null,
        "authors": null
      },
      "images": [
        {
          "url": "https://venturebeat.com/wp-content/uploads/2016/05/diagnosis-e1585691897976.jpg?fit=1200%2C600&strip=all",
          "width": 1200,
          "height": 600,
          "title": "Cordio and Rambam Hospital will trial AI that detects coronavirus cases from speech samples",
          "attribution": null
        }
      ],
      "locale": "en-us",
      "categories": [
        "news"
      ],
      "topics": [
        "AI"
      ]
    },
    {
      "path": "_news/2020-04-01-how-deepmotion-uses-ai-to-create-believable-characters.md",
      "title": "How DeepMotion uses AI to create believable characters",
      "excerpt": "As an engineer, He wanted to find an efficient way to create more lifelike animations, and he was convinced that advanced physics simulation and AI could solve that problem. So in 2014, He struck out on his own to start DeepMotion. The goal of the San Mateo, California-based company is to provide developers with powerful software development ...",
      "heat": 87,
      "tags": null,
      "type": "article",
      "webUrl": "https://venturebeat.com/2020/04/01/how-deepmotion-uses-ai-to-create-believable-characters/",
      "ampWebUrl": "https://venturebeat.com/2020/04/01/how-deepmotion-uses-ai-to-create-believable-characters/amp/",
      "cdnAmpWebUrl": "https://venturebeat-com.cdn.ampproject.org/c/s/venturebeat.com/2020/04/01/how-deepmotion-uses-ai-to-create-believable-characters/amp/",
      "publishedDateTime": "2020-04-01T01:53:00-07:00",
      "updatedDateTime": null,
      "provider": {
        "name": "VentureBeat",
        "domain": "venturebeat.com",
        "images": [
          {
            "url": "https://insideout.app/ai/assets/images/organizations/venturebeat.com-50x50.jpg",
            "width": 50,
            "height": 50,
            "title": null,
            "attribution": null
          }
        ],
        "publishers": null,
        "authors": null
      },
      "images": [
        {
          "url": "https://venturebeat.com/wp-content/uploads/2020/03/DeepMotion_VB_SS-e1585696653316.png?fit=1200%2C687&strip=all",
          "width": 1200,
          "height": 687,
          "title": "How DeepMotion uses AI to create believable characters",
          "attribution": null
        }
      ],
      "locale": "en-us",
      "categories": [
        "news"
      ],
      "topics": [
        "AI"
      ]
    },
    {
      "path": "_news/2020-04-01-algorithmic-justice-league-protests-bias-voice-ai-and-media-coverage.md",
      "title": "Algorithmic Justice League protests bias voice AI and media coverage",
      "excerpt": "“We cannot let the promise of AI overshadow real and present harms,” Benjamin said in the piece ... In statements following the release of the study, Google and IBM Watson pledged commitments to progress.",
      "heat": 91,
      "tags": null,
      "type": "article",
      "webUrl": "https://venturebeat.com/2020/03/31/algorithmic-justice-league-protests-bias-voice-ai-and-media-coverage/",
      "ampWebUrl": "https://venturebeat.com/2020/03/31/algorithmic-justice-league-protests-bias-voice-ai-and-media-coverage/amp/",
      "cdnAmpWebUrl": "https://venturebeat-com.cdn.ampproject.org/c/s/venturebeat.com/2020/03/31/algorithmic-justice-league-protests-bias-voice-ai-and-media-coverage/amp/",
      "publishedDateTime": "2020-03-31T20:48:00-07:00",
      "updatedDateTime": null,
      "provider": {
        "name": "VentureBeat",
        "domain": "venturebeat.com",
        "images": [
          {
            "url": "https://insideout.app/ai/assets/images/organizations/venturebeat.com-50x50.jpg",
            "width": 50,
            "height": 50,
            "title": null,
            "attribution": null
          }
        ],
        "publishers": null,
        "authors": null
      },
      "images": [
        {
          "url": "https://venturebeat.com/wp-content/uploads/2020/03/voicing-erasure.jpg?fit=1280%2C661&strip=all",
          "width": 1280,
          "height": 661,
          "title": "Algorithmic Justice League protests bias voice AI and media coverage",
          "attribution": null
        }
      ],
      "locale": "en-us",
      "categories": [
        "news"
      ],
      "topics": [
        "IBM AI",
        "AI",
        "Natural Language Processing"
      ]
    },
    {
      "path": "_news/2020-04-01-nvidia-a-clear-winner-in-otherwise-brutal-quarter-for-chip-makers.md",
      "title": "Nvidia a clear winner in otherwise brutal quarter for chip makers",
      "excerpt": "Last week, Needham upgraded the stock to buy, forecasting higher demand for chips used in medical applications, as well as in artificial intelligence applications. Why China’s AI champions must find alternatives to US hardware – and quick Nvidia is up about 14 per cent thus far this year, putting it in the top 10 gainers on the S&P 500.",
      "heat": 89,
      "tags": null,
      "type": "article",
      "webUrl": "https://www.scmp.com/tech/gear/article/3077869/nvidia-clear-winner-otherwise-brutal-quarter-chip-makers",
      "ampWebUrl": "https://amp.scmp.com/tech/gear/article/3077869/nvidia-clear-winner-otherwise-brutal-quarter-chip-makers",
      "cdnAmpWebUrl": "https://amp-scmp-com.cdn.ampproject.org/c/s/amp.scmp.com/tech/gear/article/3077869/nvidia-clear-winner-otherwise-brutal-quarter-chip-makers",
      "publishedDateTime": "2020-03-31T19:11:00-07:00",
      "updatedDateTime": null,
      "provider": {
        "name": "South China Morning Post",
        "domain": "scmp.com",
        "images": [
          {
            "url": "https://insideout.app/ai/assets/images/organizations/scmp.com-50x50.jpg",
            "width": 50,
            "height": 50,
            "title": null,
            "attribution": null
          }
        ],
        "publishers": null,
        "authors": null
      },
      "images": [
        {
          "url": "https://cdn.i-scmp.com/sites/default/files/styles/og_image_scmp_generic/public/d8/images/methode/2020/04/01/df04e758-73bd-11ea-ab8f-988daf8efd6f_image_hires_101133.JPG?itok=fw4QshuF&v=1585707099",
          "width": 1200,
          "height": 630,
          "title": "Nvidia a clear winner in otherwise brutal quarter for chip makers",
          "attribution": null
        }
      ],
      "locale": "en-us",
      "categories": [
        "news"
      ],
      "topics": [
        "AI Hardware",
        "AI"
      ]
    },
    {
      "path": "_news/2020-04-01-pet-care-startup-rover-lays-off-41-of-workforce-due-to-covid-19-impact.md",
      "title": "Pet care startup Rover lays off 41% of workforce due to COVID-19 impact",
      "excerpt": "Layoffs are hitting tech companies hard amid the novel coronavirus outbreak. Leafly, an online cannabis brand based in Seattle, let 91 employees go last week, while AI writing startup Textio laid off 30 people. AI marketing startup Amplero let go of 17 people and will shut down this week. Co-working startup The Riveter and clothing rental ...",
      "heat": 82,
      "tags": null,
      "type": "article",
      "webUrl": "https://www.geekwire.com/2020/pet-care-startup-rover-lays-off-41-workforce-194-employees-due-covid-19-impact/",
      "ampWebUrl": "https://www.geekwire.com/2020/pet-care-startup-rover-lays-off-41-workforce-194-employees-due-covid-19-impact/amp/",
      "cdnAmpWebUrl": "https://www-geekwire-com.cdn.ampproject.org/c/s/www.geekwire.com/2020/pet-care-startup-rover-lays-off-41-workforce-194-employees-due-covid-19-impact/amp/",
      "publishedDateTime": "2020-03-31T18:34:00-07:00",
      "updatedDateTime": null,
      "provider": {
        "name": "GeekWire",
        "domain": "geekwire.com",
        "images": [
          {
            "url": "https://insideout.app/ai/assets/images/organizations/geekwire.com-50x50.jpg",
            "width": 50,
            "height": 50,
            "title": null,
            "attribution": null
          }
        ],
        "publishers": null,
        "authors": null
      },
      "images": [
        {
          "url": "https://cdn.geekwire.com/wp-content/uploads/2020/03/rover11-630x420.jpeg",
          "width": 630,
          "height": 420,
          "title": "Pet care startup Rover lays off 41% of workforce due to COVID-19 impact",
          "attribution": null
        }
      ],
      "locale": "en-us",
      "categories": [
        "news"
      ],
      "topics": [
        "AI"
      ]
    }
  ],
  "nextPage": 2
}